[
  {
    "program": "drawer",
    "success": false
  },
  {
    "program": "google-docs",
    "success": false
  },
  {
    "program": "twitter",
    "success": false
  },
  {
    "program": "discord",
    "success": false
  },
  {
    "program": "vercel",
    "success": false
  },
  {
    "program": "sms",
    "success": false
  },
  {
    "program": "roster",
    "success": false
  },
  {
    "program": "mailchimp",
    "success": false
  },
  {
    "program": "html",
    "success": false
  },
  {
    "program": "notion",
    "success": false
  },
  {
    "program": "todo",
    "success": true
  },
  {
    "program": "google-calendar",
    "success": false
  },
  {
    "program": "slack-bot",
    "success": false
  },
  {
    "program": "pinecone",
    "success": false
  },
  {
    "program": "airtable",
    "success": false
  },
  {
    "program": "github",
    "success": false
  },
  {
    "program": "http",
    "success": false
  }
]